mujoco_ar/__init__.py
mujoco_ar/connector.py
mujoco_ar-1.4.0.dist-info/licenses/LICENSE
mujoco_ar-1.4.0.dist-info/METADATA
mujoco_ar-1.4.0.dist-info/WHEEL
mujoco_ar-1.4.0.dist-info/top_level.txt
mujoco_ar-1.4.0.dist-info/RECORD
