Metadata-Version: 2.4
Name: mujoco_ar
Version: 1.4.0
Summary: An AR controller designed to seamlessly control objects in MuJoCo and for other general uses by receiving position and rotation data from a connected iOS application.
Home-page: https://github.com/omarrayyann/mujocoar
Author: Omar Rayyan
Author-email: olr7742@nyu.edu
License: MIT
Classifier: Programming Language :: Python :: 3
Classifier: License :: OSI Approved :: MIT License
Classifier: Operating System :: OS Independent
Requires-Python: >=3.6
License-File: LICENSE
Requires-Dist: asyncio
Requires-Dist: websockets
Requires-Dist: numpy
Requires-Dist: mujoco
Dynamic: author
Dynamic: author-email
Dynamic: classifier
Dynamic: description
Dynamic: description-content-type
Dynamic: home-page
Dynamic: license
Dynamic: license-file
Dynamic: requires-dist
Dynamic: requires-python
Dynamic: summary
